ortho_poly/__init__.py
ortho_poly/polynomials.py
ortho_polys-0.1.3.dist-info/METADATA
ortho_polys-0.1.3.dist-info/WHEEL
ortho_polys-0.1.3.dist-info/top_level.txt
ortho_polys-0.1.3.dist-info/RECORD
