Metadata-Version: 2.4
Name: ortho-polys
Version: 0.1.3
Summary: Классические ортогональные полиномы: Лежандра, Чебышёва, Лагерра, Эрмита и Якоби и их свойства
Author-email: Рудаковский Евгений <alex.rudakovskii@gmail.com>
Requires-Python: >=3.8
